lightningcss-0.3.1.dist-info/METADATA
lightningcss-0.3.1.dist-info/WHEEL
lightningcss-0.3.1.dist-info/licenses/LICENSE
lightningcss/__init__.py
lightningcss/__init__.pyi
lightningcss/lightningcss.pypy311-pp73-ppc_64-linux-gnu.so
lightningcss/py.typed
lightningcss-0.3.1.dist-info/RECORD
